Workbook

Sheet Как читать
A1: Финансовая модель «Оплата вовремя» · версия для спринта 1 (28.10.2026)
A3: Жёлтые ячейки — допущения. Всё остальное считается формулами.
A4: Основная модель — сервис бесплатно встроен в интернет-банк ВТБ для МСБ. Банк зарабатывает на остатках и факторинге.
A5: Альтернатива — отдельная подписка (лист «Эффект для клиента», строки про SaaS).
A6: Значения с пометкой «гипотеза» не подтверждены. Их проверяем интервью и пилотом (см. docs/product/04_pilot.md).
A7: Высвобождение оборотных средств — разовый эффект, а не доход. Высвобождение времени — не сокращение расходов.

Sheet Допущения
A1: Параметр | B1: Пессимистичный | C1: Базовый | D1: Оптимистичный | E1: Ед. | F1: Источник / статус
A2: Клиенты МСБ ВТБ | B2: 1300000 | C2: 1300000 | D2: 1300000 | E2: компаний | F2: ВТБ, февраль 2024 (Лента.ру) — устарело, обновить по годовому отчёту
A3: Доля клиентов с B2B-продажами в отсрочку | B3: 0.3 | C3: 0.4 | D3: 0.5 | E3: доля | F3: гипотеза: 50% юрлиц и 20% ИП (оценка ресерча)
A4: Активное использование к концу 2-го года | B4: 0.01 | C4: 0.03 | D4: 0.06 | E4: доля от B2B | F4: гипотеза; ориентир — 200 тыс. пользователей Giga-ассистента СберБизнеса за год
A5: Средняя выручка клиента в месяц | B5: 4000000 | C5: 5000000 | D5: 6000000 | E5: ₽ | F5: гипотеза для малого бизнеса
A6: Сокращение срока оплаты (DSO) | B6: 2 | C6: 4 | D6: 6 | E6: дней | F6: гипотеза; Intuit заявляет 4–5 дней (вендор)
A7: Доля высвобожденных денег, оставшихся на счёте в ВТБ | B7: 0.3 | C7: 0.5 | D7: 0.6 | E7: доля | F7: гипотеза
A8: Доходность банка на остатках | B8: 0.03 | C8: 0.04 | D8: 0.05 | E8: годовых | F8: гипотеза: трансфертная маржа
A9: Конверсия активных клиентов в факторинг | B9: 0.01 | C9: 0.03 | D9: 0.05 | E9: доля в год | F9: гипотеза; сейчас факторингом пользуется <1% МСП (оценка)
A10: Средний портфель факторинга на клиента | B10: 2000000 | C10: 3000000 | D10: 4000000 | E10: ₽ | F10: гипотеза
A11: Чистая доходность факторинга для банка | B11: 0.03 | C11: 0.04 | D11: 0.05 | E11: годовых | F11: гипотеза
A12: Писем GigaChat на клиента в месяц | B12: 20 | C12: 30 | D12: 40 | E12: шт | F12: гипотеза
A13: Стоимость письма (токены) | B13: 1.5 | C13: 1 | D13: 0.75 | E13: ₽ | F13: GigaChat Pro 0,5 ₽/1K токенов, ~1,5–3K токенов на письмо
... A19: Доля активных клиентов в год 1 от целевой | B19: 0.3 | C19: 0.4 | D19: 0.5 | E19: доля | F19: плавный запуск

Sheet Экономика для банка
A1: Показатель | B1: Пессимистичный | C1: Базовый | D1: Оптимистичный | E1: Комментарий
A2: Активные клиенты, год 2 | B2: =Допущения!B2*Допущения!B3*Допущения!B4 | C2: =Допущения!C2*Допущения!C3*Допущения!C4 | D2: =Допущения!D2*Допущения!D3*Допущения!D4 | E2: клиенты × доля B2B × доля активных
A3: Активные клиенты, год 1 | B3: =B2*Допущения!B19 | C3: =C2*Допущения!C19 | D3: =D2*Допущения!D19
A4: Высвобождено денег у клиентов, год 2 | B4: =B2*Допущения!B5/30*Допущения!B6 | C4: =C2*Допущения!C5/30*Допущения!C6 | D4: =D2*Допущения!D5/30*Допущения!D6 | E4: выручка/30 × дни DSO — разово, оборотный капитал
A5: Доход банка на остатках, год 2 | B5: =B4*Допущения!B7*Допущения!B8 | C5: =C4*Допущения!C7*Допущения!C8 | D5: =D4*Допущения!D7*Допущения!D8 | E5: ₽ в год
A6: Клиентов в факторинге, год 2 | B6: =B2*Допущения!B9*2 | C6: =C2*Допущения!C9*2 | D6: =D2*Допущения!D9*2 | E6: накопленно за 2 года
A7: Доход банка от факторинга, год 2 | B7: =B6*Допущения!B10*Допущения!B11 | C7: =C6*Допущения!C10*Допущения!C11 | D7: =D6*Допущения!D10*Допущения!D11 | E7: ₽ в год
A8: Выручка банка, год 2 | B8: =B5+B7 | C8: =C5+C7 | D8: =D5+D7
A9: Переменные затраты (LLM + Jev), год 2 | B9: =B2*12*(Допущения!B12*Допущения!B13+Допущения!B14*Допущения!B15) | C9: =C2*12*(Допущения!C12*Допущения!C13+Допущения!C14*Допущения!C15) | D9: =D2*12*(Допущения!D12*Допущения!D13+Допущения!D14*Допущения!D15)
A10: Постоянные затраты, год 2 | B10: =Допущения!B18 | C10: =Допущения!C18 | D10: =Допущения!D18
A11: Операционная прибыль, год 2 | B11: =B8-B9-B10 | C11: =C8-C9-C10 | D11: =D8-D9-D10
A12: Выручка банка, год 1 | B12: =B8*Допущения!B19/2 | C12: =C8*Допущения!C19/2 | D12: =D8*Допущения!D19/2 | E12: год 1 — половина эффекта от доли активных
A13: Затраты, год 1 | B13: =Допущения!B16+Допущения!B17+B3*12*(Допущения!B12*Допущения!B13+Допущения!B14*Допущения!B15) | C13: =Допущения!C16+Допущения!C17+C3*12*(Допущения!C12*Допущения!C13+Допущения!C14*Допущения!C15) | D13: =Допущения!D16+Допущения!D17+D3*12*(Допущения!D12*Допущения!D13+Допущения!D14*Допущения!D15)
A14: Денежный поток, год 1 | B14: =B12-B13 | C14: =C12-C13 | D14: =D12-D13
A15: Накопленный поток к концу года 2 | B15: =B14+B11 | C15: =C14+C11 | D15: =D14+D11
A16: Срок окупаемости, мес. | B16: =IF(B11<=0,"не окупается",IF(B14>=0,12*B13/MAX(B12,1),12+(-B14)/(B11/12))) | C16: =IF(C11<=0,"не окупается",IF(C14>=0,12*C13/MAX(C12,1),12+(-C14)/(C11/12))) | D16: =IF(D11<=0,"не окупается",IF(D14>=0,12*D13/MAX(D12,1),12+(-D14)/(D11/12))) | E16: от старта разработки
A17: Переменные затраты на клиента в месяц | B17: =Допущения!B12*Допущения!B13+Допущения!B14*Допущения!B15 | C17: =Допущения!C12*Допущения!C13+Допущения!C14*Допущения!C15 | D17: =Допущения!D12*Допущения!D13+Допущения!D14*Допущения!D15 | E17: ₽

Sheet Эффект для клиента
A1: Параметр | B1: Значение | C1: Комментарий
A2: Выручка компании в год, ₽ | B2: 120000000 | C2: пример: проектное бюро / подрядчик
A3: Сокращение DSO, дней | B3: 4 | C3: гипотеза пилота (базовый сценарий)
A4: Ставка кредита для МСБ, годовых | B4: 0.2 | C4: ключевая 14% + маржа банка, оценка
A5: Время сотрудника на разбор одного просроченного счёта сейчас, мин | B5: 40 | C5: гипотеза — проверить в интервью
A6: Время с сервисом, мин | B6: 10 | C6: гипотеза
A7: Просроченных счетов в месяц | B7: 30 | C7: гипотеза
A8: Стоимость часа бухгалтера / финменеджера, ₽ | B8: 900 | C8: оценка с учётом взносов
A9: Высвобождено оборотных средств, ₽ | B9: =B2/365*B3 | C9: разово
A10: Экономия на процентах, ₽ в год | B10: =B9*B4 | C10: если вместо кредита — свои деньги
A11: Экономия времени, часов в год | B11: =(B5-B6)/60*B7*12
A12: Экономия времени, ₽ в год | B12: =B11*B8 | C12: высвобождение ≠ сокращение расходов
A13: Итого выгода в год, ₽ | B13: =B10+B12
A14: Цена для клиента внутри банка, ₽ в год | B14: 0 | C14: бесплатно в интернет-банке (модель для ВТБ)
A15: Цена standalone SaaS, ₽ в год | B15: 18000 | C15: ориентир 1 500 ₽/мес; ПланФакт от 4 484 ₽/мес
A16: Окупаемость подписки SaaS, мес. | B16: =B15/(B13/12)

Sheet Рынок TAM-SAM-SOM
A1: Уровень | B1: Расчёт | C1: Значение, ₽ в год | D1: Комментарий
A2: Юрлица МСП | C2: 2020000 | D2: Реестр МСП 10.07.2026 (ОПОРА)
A3: ИП | C3: 4590000 | D3: там же
A4: Доля с B2B-выручкой: юрлица / ИП | C4: 50% / 20% | D4: гипотеза
A5: Компаний в TAM | B5: =C2*0.5+C3*0.2 | C5: =C2*0.5+C3*0.2
A6: ARPU, ₽ в месяц | C6: 1500 | D6: гипотеза; ориентир рынка учётного ПО
A7: TAM | B7: компании × ARPU × 12 | C7: =C5*C6*12 | D7: весь российский B2B-МСБ
A8: SAM (клиенты ВТБ с B2B) | B8: 1,3 млн × 0,4 × ARPU × 12 | C8: =1300000*0.4*C6*12 | D8: устаревшее число клиентов ВТБ
A9: SOM (3 года, 3% SAM) | B9: SAM × 3% | C9: =C8*0.03 | D9: базовый сценарий
